pustota_pygments/__init__.py
pustota_pygments/py.typed
pustota_pygments-0.1.1.dist-info/LICENSE
pustota_pygments-0.1.1.dist-info/METADATA
pustota_pygments-0.1.1.dist-info/WHEEL
pustota_pygments-0.1.1.dist-info/entry_points.txt
pustota_pygments-0.1.1.dist-info/RECORD
