Metadata-Version: 2.3
Name: pustota-pygments
Version: 0.1.1
Summary: pustota theme for pygments for code highlighting
License: MIT
Keywords: pygments,pygments-theme,pygments-style,style,code highlight,keynotes
Author: Nikita Sobolev
Author-email: mail@sobolevn.me
Requires-Python: >=3.10,<3.14
Classifier: Development Status :: 3 - Alpha
Classifier: Intended Audience :: Developers
Classifier: License :: OSI Approved :: MIT License
Classifier: Operating System :: OS Independent
Classifier: Programming Language :: Python :: 3
Classifier: Programming Language :: Python :: 3.10
Classifier: Programming Language :: Python :: 3.11
Classifier: Programming Language :: Python :: 3.12
Classifier: Programming Language :: Python :: 3.13
Classifier: Topic :: Software Development :: Libraries :: Python Modules
Requires-Dist: pygments (>=2.19,<3.0)
